service_capacity_modeling/__init__.py
service_capacity_modeling/capacity_planner.py
service_capacity_modeling/enum_utils.py
service_capacity_modeling/interface.py
service_capacity_modeling/stats.py
service_capacity_modeling/hardware/__init__.py
service_capacity_modeling/hardware/profiles/__init__.py
service_capacity_modeling/hardware/profiles/profiles.txt
service_capacity_modeling/hardware/profiles/pricing/aws/3yr-reserved_ec2.json
service_capacity_modeling/hardware/profiles/pricing/aws/3yr-reserved_rds.json
service_capacity_modeling/hardware/profiles/pricing/aws/3yr-reserved_zz-overrides.json
service_capacity_modeling/hardware/profiles/shapes/aws/auto_c5.json
service_capacity_modeling/hardware/profiles/shapes/aws/auto_c5a.json
service_capacity_modeling/hardware/profiles/shapes/aws/auto_c5d.json
service_capacity_modeling/hardware/profiles/shapes/aws/auto_c5n.json
service_capacity_modeling/hardware/profiles/shapes/aws/auto_c6a.json
service_capacity_modeling/hardware/profiles/shapes/aws/auto_c6i.json
service_capacity_modeling/hardware/profiles/shapes/aws/auto_c6id.json
service_capacity_modeling/hardware/profiles/shapes/aws/auto_c7a.json
service_capacity_modeling/hardware/profiles/shapes/aws/auto_c7i.json
service_capacity_modeling/hardware/profiles/shapes/aws/auto_c8i.json
service_capacity_modeling/hardware/profiles/shapes/aws/auto_db_r6g.json
service_capacity_modeling/hardware/profiles/shapes/aws/auto_db_r6i.json
service_capacity_modeling/hardware/profiles/shapes/aws/auto_db_r7g.json
service_capacity_modeling/hardware/profiles/shapes/aws/auto_db_r7i.json
service_capacity_modeling/hardware/profiles/shapes/aws/auto_i3en.json
service_capacity_modeling/hardware/profiles/shapes/aws/auto_i4i.json
service_capacity_modeling/hardware/profiles/shapes/aws/auto_i7i.json
service_capacity_modeling/hardware/profiles/shapes/aws/auto_m4.json
service_capacity_modeling/hardware/profiles/shapes/aws/auto_m5.json
service_capacity_modeling/hardware/profiles/shapes/aws/auto_m5n.json
service_capacity_modeling-0.3.107.dist-info/licenses/LICENSE
service_capacity_modeling-0.3.107.dist-info/METADATA
service_capacity_modeling-0.3.107.dist-info/WHEEL
service_capacity_modeling-0.3.107.dist-info/entry_points.txt
service_capacity_modeling-0.3.107.dist-info/top_level.txt
service_capacity_modeling-0.3.107.dist-info/RECORD
