Metadata-Version: 2.4
Name: service-capacity-modeling
Version: 0.3.107
Summary: Contains utilities for modeling capacity for pluggable workloads
Author: Joseph Lynch
Author-email: josephl@netflix.com
License: Apache 2.0
Classifier: Programming Language :: Python :: 3
Classifier: Programming Language :: Python :: 3.10
Classifier: Programming Language :: Python :: 3.11
Classifier: Programming Language :: Python :: 3.12
Classifier: License :: OSI Approved :: Apache Software License
Classifier: Operating System :: OS Independent
Requires-Python: >=3.10,<3.13
License-File: LICENSE
Requires-Dist: pydantic>2.0
Requires-Dist: scipy
Requires-Dist: numpy
Requires-Dist: isodate
Provides-Extra: aws
Requires-Dist: boto3; extra == "aws"
Dynamic: author
Dynamic: author-email
Dynamic: classifier
Dynamic: description
Dynamic: description-content-type
Dynamic: license
Dynamic: license-file
Dynamic: provides-extra
Dynamic: requires-dist
Dynamic: requires-python
Dynamic: summary
